[
  {
    "product_id": 1868,
    "product_title": "Wallet",
    "category": "Wallet",
    "image_url": "https://m.media-amazon.com/images/I/91XccsbCb1L._AC_UL320_.jpg",
    "product_description": "Oliver RFID Blocking Black Leather Wallet for Men",
    "price": 494,
    "stock": 149,
    "color": "Black"
  },
  {
    "product_id": 1821,
    "product_title": "Wallet",
    "category": "Wallet",
    "image_url": "https://m.media-amazon.com/images/I/61oKU8wQcRL._AC_UL320_.jpg",
    "product_description": "Men's Artificial Leather Wallet (Black)",
    "price": 173,
    "stock": 52,
    "color": "Black"
  },
  {
    "product_id": 1904,
    "product_title": "Wallet",
    "category": "Wallet",
    "image_url": "https://m.media-amazon.com/images/I/81TsFd6RMXL._AC_UL320_.jpg",
    "product_description": "RFID Protected Genuine High Quality Leather Wallet for Men(Black)",
    "price": 299,
    "stock": 90,
    "color": "Black"
  },
  {
    "product_id": 1925,
    "product_title": "Wallet",
    "category": "Wallet",
    "image_url": "https://m.media-amazon.com/images/I/7198sxW3gnL._AC_UL320_.jpg",
    "product_description": "RFID Protected Genuine Leather Wallet for Men(Black)",
    "price": 486,
    "stock": 146,
    "color": "Black"
  },
  {
    "product_id": 1858,
    "product_title": "Wallet",
    "category": "Wallet",
    "image_url": "https://m.media-amazon.com/images/I/81ecSfN2OOL._AC_UL320_.jpg",
    "product_description": "Branded Stylish Black Men's Genuine Leather Wallet/Purse",
    "price": 299,
    "stock": 90,
    "color": "Black"
  },
  {
    "product_id": 1880,
    "product_title": "Wallet",
    "category": "Wallet",
    "image_url": "https://m.media-amazon.com/images/I/91tP5mzd9QL._AC_UL320_.jpg",
    "product_description": "Leather Men's Money Clip (UBF111PBL1031_Black & Papaya)",
    "price": 494,
    "stock": 149,
    "color": "Black"
  },
  {
    "product_id": 1900,
    "product_title": "Wallet",
    "category": "Wallet",
    "image_url": "https://m.media-amazon.com/images/I/91cD7106X4L._AC_UL320_.jpg",
    "product_description": "RFID Protected Genuine High Quality Leather Wallet for Men (Black)",
    "price": 299,
    "stock": 90,
    "color": "Black"
  },
  {
    "product_id": 1820,
    "product_title": "Wallet",
    "category": "Wallet",
    "image_url": "https://m.media-amazon.com/images/I/91BEbdklpfL._AC_UL320_.jpg",
    "product_description": "Kyle RFID Blocking Black/Redwood Leather Wallet for Men",
    "price": 494,
    "stock": 149,
    "color": "Black"
  },
  {
    "product_id": 1842,
    "product_title": "Wallet",
    "category": "Wallet",
    "image_url": "https://m.media-amazon.com/images/I/81WJ8hglzfL._AC_UL320_.jpg",
    "product_description": "Men's RFID Protected Genuine Leather Wallet (Black)",
    "price": 370,
    "stock": 112,
    "color": "Black"
  },
  {
    "product_id": 1876,
    "product_title": "Wallet",
    "category": "Wallet",
    "image_url": "https://m.media-amazon.com/images/I/81pNC-fsgHL._AC_UL320_.jpg",
    "product_description": "Brian Black Leather Wallet & Black Casual Belt Combo Gift Set for Men",
    "price": 854,
    "stock": 257,
    "color": "Black"
  },
  {
    "product_id": 1912,
    "product_title": "Wallet",
    "category": "Wallet",
    "image_url": "https://m.media-amazon.com/images/I/7198sxW3gnL._AC_UL320_.jpg",
    "product_description": "RFID Protected Genuine High Quality Leather Wallet for Men(Black)",
    "price": 486,
    "stock": 146,
    "color": "Black"
  },
  {
    "product_id": 1848,
    "product_title": "Wallet",
    "category": "Wallet",
    "image_url": "https://m.media-amazon.com/images/I/41+OZS9-k1L._AC_UL320_.jpg",
    "product_description": "RFID Protected Black Leather Wallet",
    "price": 440,
    "stock": 133,
    "color": "Black"
  },
  {
    "product_id": 1845,
    "product_title": "Wallet",
    "category": "Wallet",
    "image_url": "https://m.media-amazon.com/images/I/7198sxW3gnL._AC_UL320_.jpg",
    "product_description": "RFID Men's Protected River Genuine Leather Wallet (Black)",
    "price": 399,
    "stock": 120,
    "color": "Black"
  },
  {
    "product_id": 1823,
    "product_title": "Wallet",
    "category": "Wallet",
    "image_url": "https://m.media-amazon.com/images/I/817z4KSgvRL._AC_UL320_.jpg",
    "product_description": "RFID Protected Genuine High Quality Leather Wallet & Pen Combo for Men…",
    "price": 475,
    "stock": 143,
    "color": "Black"
  },
  {
    "product_id": 1851,
    "product_title": "Wallet",
    "category": "Wallet",
    "image_url": "https://m.media-amazon.com/images/I/71oOCZudfPL._AC_UL320_.jpg",
    "product_description": "Mens Black Wallet and Belt Combo Gift Set for Men BW93118",
    "price": 892,
    "stock": 268,
    "color": "Black"
  },
  {
    "product_id": 1864,
    "product_title": "Wallet",
    "category": "Wallet",
    "image_url": "https://m.media-amazon.com/images/I/91LLc4LfGkL._AC_UL320_.jpg",
    "product_description": "Money Clip Wallet for Men Genuine Leather Branded Stylish Bi-Fold Slim Coal Black Handmade Genuine Leather with Card Holders.",
    "price": 499,
    "stock": 150,
    "color": "Black"
  },
  {
    "product_id": 1862,
    "product_title": "Wallet",
    "category": "Wallet",
    "image_url": "https://m.media-amazon.com/images/I/71GhWZCPFuL._AC_UL320_.jpg",
    "product_description": "Maddison Men's Black Genuine Leather Wallet",
    "price": 422,
    "stock": 127,
    "color": "Black"
  },
  {
    "product_id": 1882,
    "product_title": "Wallet",
    "category": "Wallet",
    "image_url": "https://m.media-amazon.com/images/I/7115wWkXL+L._AC_UL320_.jpg",
    "product_description": "Denial Black Mens Leather Wallet – Premium Quality Leather Wallet for Mens & RFID Blocking Genuine Leather Mens Wallet",
    "price": 563,
    "stock": 169,
    "color": "Black"
  },
  {
    "product_id": 1801,
    "product_title": "Wallet",
    "category": "Wallet",
    "image_url": "https://m.media-amazon.com/images/I/81YWFxEOX8L._AC_UL320_.jpg",
    "product_description": "Oliver Mens Leather Wallet",
    "price": 494,
    "stock": 149,
    "color": "Grey"
  },
  {
    "product_id": 1933,
    "product_title": "Wallet",
    "category": "Wallet",
    "image_url": "https://m.media-amazon.com/images/I/81BH1pQ7MWL._AC_UL320_.jpg",
    "product_description": "Brian Grey Leather Wallet & Grey Casual Belt Combo Gift Set for Men",
    "price": 949,
    "stock": 285,
    "color": "Grey"
  },
  {
    "product_id": 1883,
    "product_title": "Wallet",
    "category": "Wallet",
    "image_url": "https://m.media-amazon.com/images/I/814O-sqT98L._AC_UL320_.jpg",
    "product_description": "Leather Men's Money Clip (UBF149GLG1031_Green)",
    "price": 494,
    "stock": 149,
    "color": "Grey"
  },
  {
    "product_id": 1886,
    "product_title": "Wallet",
    "category": "Wallet",
    "image_url": "https://m.media-amazon.com/images/I/81t4OnMEpuL._AC_UL320_.jpg",
    "product_description": "Genuine Leather Bifold RFID Protected Credit Debit Card Holder Wallet for Men Women, Blue Grey",
    "price": 299,
    "stock": 90,
    "color": "Grey"
  },
  {
    "product_id": 1867,
    "product_title": "Wallet",
    "category": "Wallet",
    "image_url": "https://m.media-amazon.com/images/I/61jM9aB318L._AC_UL320_.jpg",
    "product_description": "Men's Money Clip Leather Bi-Fold Slim Wallet with Card Holder & Money Clipper. (Ash Grey)",
    "price": 499,
    "stock": 150,
    "color": "Grey"
  },
  {
    "product_id": 1915,
    "product_title": "Wallet",
    "category": "Wallet",
    "image_url": "https://m.media-amazon.com/images/I/811FkyWBf6L._AC_UL320_.jpg",
    "product_description": "RFID Protected Genuine High Quality Leather Wallet for Men (Grey Hunter)",
    "price": 399,
    "stock": 120,
    "color": "Grey"
  },
  {
    "product_id": 1913,
    "product_title": "Wallet",
    "category": "Wallet",
    "image_url": "https://m.media-amazon.com/images/I/810bWbCKAZL._AC_UL320_.jpg",
    "product_description": "Themes Grey Mens Leather Wallet – Premium Quality Leather Wallet for Mens and RFID Blocking Genuine Leather Mens Wallet",
    "price": 516,
    "stock": 155,
    "color": "Grey"
  },
  {
    "product_id": 1852,
    "product_title": "Wallet",
    "category": "Wallet",
    "image_url": "https://m.media-amazon.com/images/I/71jSqDIWlkL._AC_UL320_.jpg",
    "product_description": "Men's Stella Grey Genuine Leather RFID Blocking Wallet",
    "price": 516,
    "stock": 155,
    "color": "Grey"
  },
  {
    "product_id": 1899,
    "product_title": "Wallet",
    "category": "Wallet",
    "image_url": "https://m.media-amazon.com/images/I/61YDCXriSWL._AC_UL320_.jpg",
    "product_description": "Croco Texture Wallet (Grey)",
    "price": 599,
    "stock": 180,
    "color": "Grey"
  },
  {
    "product_id": 1817,
    "product_title": "Wallet",
    "category": "Wallet",
    "image_url": "https://m.media-amazon.com/images/I/71ywiiClC9L._AC_UL320_.jpg",
    "product_description": "Grey Leather Wallet & Black Reversible Belt Combo Gift Set for Men",
    "price": 498,
    "stock": 150,
    "color": "Grey"
  },
  {
    "product_id": 1865,
    "product_title": "Wallet",
    "category": "Wallet",
    "image_url": "https://m.media-amazon.com/images/I/81wmYly5E2L._AC_UL320_.jpg",
    "product_description": "Leather Wallet (UBF130GRY1018_Grey)",
    "price": 494,
    "stock": 149,
    "color": "Grey"
  },
  {
    "product_id": 1923,
    "product_title": "Wallet",
    "category": "Wallet",
    "image_url": "https://m.media-amazon.com/images/I/91DbrvZX8PL._AC_UL320_.jpg",
    "product_description": "Henry Taupe Wallet and Belt Combo Gift Set for Men - Classic Taupe Leather Wallet and Leather Belt Combo",
    "price": 854,
    "stock": 257,
    "color": "Grey"
  },
  {
    "product_id": 1909,
    "product_title": "Wallet",
    "category": "Wallet",
    "image_url": "https://m.media-amazon.com/images/I/81FpEBJqeML._AC_UL320_.jpg",
    "product_description": "Ben Grey Wallet and Belt Combo Gift Set for Men",
    "price": 854,
    "stock": 257,
    "color": "Grey"
  },
  {
    "product_id": 1861,
    "product_title": "Wallet",
    "category": "Wallet",
    "image_url": "https://m.media-amazon.com/images/I/81MwvymY6ZL._AC_UL320_.jpg",
    "product_description": "PU Leather Men's Wallet (Men wallet_Grey_Grey)",
    "price": 845,
    "stock": 254,
    "color": "Grey"
  },
  {
    "product_id": 1834,
    "product_title": "Wallet",
    "category": "Wallet",
    "image_url": "https://m.media-amazon.com/images/I/81yuwAndkzL._AC_UL320_.jpg",
    "product_description": "Carl Leather Men's Wallet (UBF130GRY1021_Grey).",
    "price": 449,
    "stock": 135,
    "color": "Grey"
  },
  {
    "product_id": 1841,
    "product_title": "Wallet",
    "category": "Wallet",
    "image_url": "https://m.media-amazon.com/images/I/71uyG8bvz5L._AC_UL320_.jpg",
    "product_description": "Vegan Leather Grey Men's Wallet with RFID Protection and Zipper Lock",
    "price": 329,
    "stock": 99,
    "color": "Grey"
  },
  {
    "product_id": 1856,
    "product_title": "Wallet",
    "category": "Wallet",
    "image_url": "https://m.media-amazon.com/images/I/81fwpwJG8RL._AC_UL320_.jpg",
    "product_description": "Regular Men's Wallet Unisex Casual Wallet, Solid Leather 3 FOLD Gents Wallet (Grey)",
    "price": 340,
    "stock": 103,
    "color": "Grey"
  },
  {
    "product_id": 1924,
    "product_title": "Wallet",
    "category": "Wallet",
    "image_url": "https://m.media-amazon.com/images/I/81UWvolwq+L._AC_UL320_.jpg",
    "product_description": "Regular Wallet for Men and Women (Unisex) Casual,Slim Solid Leather 3 FOLD tri Folded Wallet (Grey)",
    "price": 340,
    "stock": 103,
    "color": "Grey"
  }
]